recursor_mcp_server/__init__.py
recursor_mcp_server/__main__.py
recursor_mcp_server/cli.py
recursor_mcp_server/client.py
recursor_mcp_server/http_bridge.py
recursor_mcp_server/resources.py
recursor_mcp_server/server.py
recursor_mcp_server/tools.py
recursor_mcp_server-1.4.3.dist-info/METADATA
recursor_mcp_server-1.4.3.dist-info/WHEEL
recursor_mcp_server-1.4.3.dist-info/entry_points.txt
recursor_mcp_server-1.4.3.dist-info/licenses/LICENSE
recursor_mcp_server-1.4.3.dist-info/RECORD
