Metadata-Version: 2.4
Name: recursor-mcp-server
Version: 1.4.3
Summary: Recursor MCP (Model Context Protocol) Server - Connect AI assistants (Claude Desktop, Cursor) to your Recursor project's memory
Project-URL: Homepage, https://recursor.dev
Project-URL: Documentation, https://docs.recursor.dev/mcp
Project-URL: Repository, https://github.com/recursor/middleware
Project-URL: Issues, https://github.com/recursor/middleware/issues
Author-email: Recursor <team@recursor.dev>
Maintainer-email: Recursor <team@recursor.dev>
License: MIT License
License-File: LICENSE
Keywords: ai,ai-assistant,claude,context,cursor,llm,mcp,memory,model-context-protocol,recursor
Classifier: Development Status :: 4 - Beta
Classifier: Intended Audience :: Developers
Classifier: License :: OSI Approved :: MIT License
Classifier: Operating System :: OS Independent
Classifier: Programming Language :: Python :: 3
Classifier: Programming Language :: Python :: 3.10
Classifier: Programming Language :: Python :: 3.11
Classifier: Programming Language :: Python :: 3.12
Classifier: Topic :: Scientific/Engineering :: Artificial Intelligence
Classifier: Topic :: Software Development :: Libraries :: Python Modules
Classifier: Typing :: Typed
Requires-Python: >=3.10
Requires-Dist: aiohttp>=3.9.0
Requires-Dist: asyncpg>=0.29.0
Requires-Dist: mcp>=0.1.0
Requires-Dist: python-dotenv>=1.0.0
Requires-Dist: sqlalchemy>=2.0.0
Provides-Extra: http
Requires-Dist: fastapi>=0.100.0; extra == 'http'
Requires-Dist: uvicorn>=0.23.0; extra == 'http'
Requires-Dist: websockets<13,>=12.0; extra == 'http'
Provides-Extra: test
Requires-Dist: pytest-asyncio>=0.21.0; extra == 'test'
Requires-Dist: pytest>=7.4.0; extra == 'test'
